mscp_client/__init__.py
mscp_client/__pycache__/__init__.cpython-310.pyc
mscp_client-0.0.4.dist-info/LICENSE
mscp_client-0.0.4.dist-info/METADATA
mscp_client-0.0.4.dist-info/WHEEL
mscp_client-0.0.4.dist-info/top_level.txt
mscp_client-0.0.4.dist-info/RECORD
