Metadata-Version: 2.1
Name: mscp-client
Version: 0.0.4
Summary: Client for MSCP DB
Author-email: Hays Barrett <hbarrett@edac.unm.edu>
Classifier: Programming Language :: Python :: 3
Requires-Python: >=3.7
License-File: LICENSE
Requires-Dist: sqlalchemy
Requires-Dist: pandas
Requires-Dist: numpy
